__init__.py
import_surgeon/__init__.py
import_surgeon/banner.py
import_surgeon/cli.py
import_surgeon/modules/__init__.py
import_surgeon/modules/analysis.py
import_surgeon/modules/config.py
import_surgeon/modules/cst_utils.py
import_surgeon/modules/encoding.py
import_surgeon/modules/file_ops.py
import_surgeon/modules/git_ops.py
import_surgeon/modules/interactive.py
import_surgeon/modules/process.py
import_surgeon/modules/rollback.py
import_surgeon-4.0.1.dist-info/METADATA
import_surgeon-4.0.1.dist-info/WHEEL
import_surgeon-4.0.1.dist-info/entry_points.txt
import_surgeon-4.0.1.dist-info/top_level.txt
import_surgeon-4.0.1.dist-info/RECORD
