Metadata-Version: 2.4
Name: import-surgeon
Version: 4.0.1
Summary: Precision import refactoring tool — rewrite, migrate, and sanitize Python imports project-wide with safety and accuracy.
Author-email: Dhruv <dhruv13x@gmail.com>
Maintainer-email: Dhruv <dhruv13x@gmail.com>
License: MIT
Project-URL: Homepage, https://github.com/dhruv13x/import-surgeon
Project-URL: Repository, https://github.com/dhruv13x/import-surgeon.git
Project-URL: Issues, https://github.com/dhruv13x/import-surgeon/issues
Keywords: import,refactoring,code-mod,import-fix,migration,developer-tools,automatic-refactor,cli,python-tooling
Classifier: Development Status :: 4 - Beta
Classifier: Environment :: Console
Classifier: Intended Audience :: Developers
Classifier: Topic :: Software Development :: Code Generators
Classifier: Topic :: Software Development :: Libraries
Classifier: Topic :: Software Development :: Build Tools
Classifier: License :: OSI Approved :: MIT License
Classifier: Operating System :: OS Independent
Classifier: Programming Language :: Python :: 3
Classifier: Programming Language :: Python :: 3 :: Only
Requires-Python: >=3.8
Requires-Dist: rich>=13.0
Requires-Dist: tqdm>=4.66
Requires-Dist: pyyaml>=6.0
Requires-Dist: regex>=2024.7
Requires-Dist: black>=24.0
Requires-Dist: isort>=5.13
Requires-Dist: libcst>=1.0.0
Provides-Extra: dev
Requires-Dist: pytest>=8.0.0; extra == "dev"
Requires-Dist: pytest-cov>=5.0.0; extra == "dev"
Requires-Dist: pytest-timeout>=2.2.0; extra == "dev"
Requires-Dist: pytest-json-report>=1.5.0; extra == "dev"
Requires-Dist: pytest-asyncio>=0.23.0; extra == "dev"
Requires-Dist: pytest-mock>=3.10.0; extra == "dev"
Requires-Dist: pyfakefs>=5.0.0; extra == "dev"
Requires-Dist: ruff>=0.6.0; extra == "dev"
Requires-Dist: black>=24.3.0; extra == "dev"
Requires-Dist: mypy>=1.11.0; extra == "dev"
Requires-Dist: PyYAML>=6.0; extra == "dev"
Requires-Dist: types-PyYAML>=6.0; extra == "dev"
